FormatDefault/__init__.py
FormatDefault-1.0.1.dist-info/LICENSE
FormatDefault-1.0.1.dist-info/METADATA
FormatDefault-1.0.1.dist-info/WHEEL
FormatDefault-1.0.1.dist-info/top_level.txt
FormatDefault-1.0.1.dist-info/RECORD
