Metadata-Version: 2.1
Name: FormatDefault
Version: 1.0.1
Summary: str.format but with default values
License: GNU GENERAL PUBLIC LICENSE
Project-URL: Homepage, https://github.com/jb2170/FormatDefault/
License-File: LICENSE
